{"state_code":"US_DEMO","officer_external_id":"123","absconsion_count":"1","felony_count":"1","technical_count":"1","unknown_count":"0"}
{"state_code":"US_DEMO","officer_external_id":"234","absconsion_count":"2","felony_count":"3","technical_count":"2","unknown_count":"0"}
{"state_code":"US_DEMO","officer_external_id":"345","absconsion_count":"0","felony_count":"2","technical_count":"2","unknown_count":"0"}
{"state_code":"US_DEMO","officer_external_id":"456","absconsion_count":"0","felony_count":"1","technical_count":"0","unknown_count":"1"}
{"state_code":"US_DEMO","officer_external_id":"567","absconsion_count":"1","felony_count":"3","technical_count":"1","unknown_count":"0"}
{"state_code":"US_DEMO","officer_external_id":"678","absconsion_count":"0","felony_count":"0","technical_count":"1","unknown_count":"1"}
{"state_code":"US_DEMO","officer_external_id":"789","absconsion_count":"2","felony_count":"2","technical_count":"0","unknown_count":"0"}
{"state_code":"US_DEMO","officer_external_id":"890","absconsion_count":"0","felony_count":"0","technical_count":"0","unknown_count":"1"}
{"state_code":"US_DEMO","officer_external_id":"901","absconsion_count":"0","felony_count":"1","technical_count":"0","unknown_count":"0"}
{"state_code":"US_DEMO","officer_external_id":"012","absconsion_count":"1","felony_count":"0","technical_count":"0","unknown_count":"0"}
