{"state_code":"US_DEMO","violation_type":"TECHNICAL","reported_violations":1,"risk_level":"LOW","population_count":22}
{"state_code":"US_DEMO","violation_type":"TECHNICAL","reported_violations":1,"risk_level":"MODERATE","population_count":null}
{"state_code":"US_DEMO","violation_type":"TECHNICAL","reported_violations":1,"risk_level":"HIGH","population_count":null}
{"state_code":"US_DEMO","violation_type":"TECHNICAL","reported_violations":1,"risk_level":"VERY_HIGH","population_count":2}
{"state_code":"US_DEMO","violation_type":"TECHNICAL","reported_violations":2,"risk_level":"LOW","population_count":1}
{"state_code":"US_DEMO","violation_type":"TECHNICAL","reported_violations":2,"risk_level":"MODERATE","population_count":null}
{"state_code":"US_DEMO","violation_type":"TECHNICAL","reported_violations":2,"risk_level":"HIGH","population_count":4}
{"state_code":"US_DEMO","violation_type":"TECHNICAL","reported_violations":2,"risk_level":"VERY_HIGH","population_count":12}
{"state_code":"US_DEMO","violation_type":"TECHNICAL","reported_violations":3,"risk_level":"LOW","population_count":20}
{"state_code":"US_DEMO","violation_type":"TECHNICAL","reported_violations":3,"risk_level":"MODERATE","population_count":null}
{"state_code":"US_DEMO","violation_type":"TECHNICAL","reported_violations":3,"risk_level":"HIGH","population_count":2}
{"state_code":"US_DEMO","violation_type":"TECHNICAL","reported_violations":3,"risk_level":"VERY_HIGH","population_count":22}
{"state_code":"US_DEMO","violation_type":"TECHNICAL","reported_violations":4,"risk_level":"LOW","population_count":16}
{"state_code":"US_DEMO","violation_type":"TECHNICAL","reported_violations":4,"risk_level":"MODERATE","population_count":3}
{"state_code":"US_DEMO","violation_type":"TECHNICAL","reported_violations":4,"risk_level":"HIGH","population_count":null}
{"state_code":"US_DEMO","violation_type":"TECHNICAL","reported_violations":4,"risk_level":"VERY_HIGH","population_count":18}
{"state_code":"US_DEMO","violation_type":"TECHNICAL","reported_violations":5,"risk_level":"LOW","population_count":null}
{"state_code":"US_DEMO","violation_type":"TECHNICAL","reported_violations":5,"risk_level":"MODERATE","population_count":20}
{"state_code":"US_DEMO","violation_type":"TECHNICAL","reported_violations":5,"risk_level":"HIGH","population_count":4}
{"state_code":"US_DEMO","violation_type":"TECHNICAL","reported_violations":5,"risk_level":"VERY_HIGH","population_count":null}
{"state_code":"US_DEMO","violation_type":"TECHNICAL","reported_violations":6,"risk_level":"LOW","population_count":22}
{"state_code":"US_DEMO","violation_type":"TECHNICAL","reported_violations":6,"risk_level":"MODERATE","population_count":23}
{"state_code":"US_DEMO","violation_type":"TECHNICAL","reported_violations":6,"risk_level":"HIGH","population_count":15}
{"state_code":"US_DEMO","violation_type":"TECHNICAL","reported_violations":6,"risk_level":"VERY_HIGH","population_count":6}
{"state_code":"US_DEMO","violation_type":"TECHNICAL","reported_violations":7,"risk_level":"LOW","population_count":14}
{"state_code":"US_DEMO","violation_type":"TECHNICAL","reported_violations":7,"risk_level":"MODERATE","population_count":3}
{"state_code":"US_DEMO","violation_type":"TECHNICAL","reported_violations":7,"risk_level":"HIGH","population_count":null}
{"state_code":"US_DEMO","violation_type":"TECHNICAL","reported_violations":7,"risk_level":"VERY_HIGH","population_count":23}
{"state_code":"US_DEMO","violation_type":"TECHNICAL","reported_violations":8,"risk_level":"LOW","population_count":25}
{"state_code":"US_DEMO","violation_type":"TECHNICAL","reported_violations":8,"risk_level":"MODERATE","population_count":10}
{"state_code":"US_DEMO","violation_type":"TECHNICAL","reported_violations":8,"risk_level":"HIGH","population_count":23}
{"state_code":"US_DEMO","violation_type":"TECHNICAL","reported_violations":8,"risk_level":"VERY_HIGH","population_count":3}
{"state_code":"US_DEMO","violation_type":"MUNICIPAL","reported_violations":1,"risk_level":"LOW","population_count":15}
{"state_code":"US_DEMO","violation_type":"MUNICIPAL","reported_violations":1,"risk_level":"MODERATE","population_count":null}
{"state_code":"US_DEMO","violation_type":"MUNICIPAL","reported_violations":1,"risk_level":"HIGH","population_count":16}
{"state_code":"US_DEMO","violation_type":"MUNICIPAL","reported_violations":1,"risk_level":"VERY_HIGH","population_count":null}
{"state_code":"US_DEMO","violation_type":"MUNICIPAL","reported_violations":2,"risk_level":"LOW","population_count":17}
{"state_code":"US_DEMO","violation_type":"MUNICIPAL","reported_violations":2,"risk_level":"MODERATE","population_count":4}
{"state_code":"US_DEMO","violation_type":"MUNICIPAL","reported_violations":2,"risk_level":"HIGH","population_count":23}
{"state_code":"US_DEMO","violation_type":"MUNICIPAL","reported_violations":2,"risk_level":"VERY_HIGH","population_count":18}
{"state_code":"US_DEMO","violation_type":"MUNICIPAL","reported_violations":3,"risk_level":"LOW","population_count":17}
{"state_code":"US_DEMO","violation_type":"MUNICIPAL","reported_violations":3,"risk_level":"MODERATE","population_count":2}
{"state_code":"US_DEMO","violation_type":"MUNICIPAL","reported_violations":3,"risk_level":"HIGH","population_count":9}
{"state_code":"US_DEMO","violation_type":"MUNICIPAL","reported_violations":3,"risk_level":"VERY_HIGH","population_count":1}
{"state_code":"US_DEMO","violation_type":"MUNICIPAL","reported_violations":4,"risk_level":"LOW","population_count":3}
{"state_code":"US_DEMO","violation_type":"MUNICIPAL","reported_violations":4,"risk_level":"MODERATE","population_count":null}
{"state_code":"US_DEMO","violation_type":"MUNICIPAL","reported_violations":4,"risk_level":"HIGH","population_count":null}
{"state_code":"US_DEMO","violation_type":"MUNICIPAL","reported_violations":4,"risk_level":"VERY_HIGH","population_count":4}
{"state_code":"US_DEMO","violation_type":"MUNICIPAL","reported_violations":5,"risk_level":"LOW","population_count":1}
{"state_code":"US_DEMO","violation_type":"MUNICIPAL","reported_violations":5,"risk_level":"MODERATE","population_count":18}
{"state_code":"US_DEMO","violation_type":"MUNICIPAL","reported_violations":5,"risk_level":"HIGH","population_count":18}
{"state_code":"US_DEMO","violation_type":"MUNICIPAL","reported_violations":5,"risk_level":"VERY_HIGH","population_count":12}
{"state_code":"US_DEMO","violation_type":"MUNICIPAL","reported_violations":6,"risk_level":"LOW","population_count":null}
{"state_code":"US_DEMO","violation_type":"MUNICIPAL","reported_violations":6,"risk_level":"MODERATE","population_count":17}
{"state_code":"US_DEMO","violation_type":"MUNICIPAL","reported_violations":6,"risk_level":"HIGH","population_count":25}
{"state_code":"US_DEMO","violation_type":"MUNICIPAL","reported_violations":6,"risk_level":"VERY_HIGH","population_count":24}
{"state_code":"US_DEMO","violation_type":"MUNICIPAL","reported_violations":7,"risk_level":"LOW","population_count":null}
{"state_code":"US_DEMO","violation_type":"MUNICIPAL","reported_violations":7,"risk_level":"MODERATE","population_count":7}
{"state_code":"US_DEMO","violation_type":"MUNICIPAL","reported_violations":7,"risk_level":"HIGH","population_count":16}
{"state_code":"US_DEMO","violation_type":"MUNICIPAL","reported_violations":7,"risk_level":"VERY_HIGH","population_count":18}
{"state_code":"US_DEMO","violation_type":"MUNICIPAL","reported_violations":8,"risk_level":"LOW","population_count":3}
{"state_code":"US_DEMO","violation_type":"MUNICIPAL","reported_violations":8,"risk_level":"MODERATE","population_count":7}
{"state_code":"US_DEMO","violation_type":"MUNICIPAL","reported_violations":8,"risk_level":"HIGH","population_count":19}
{"state_code":"US_DEMO","violation_type":"MUNICIPAL","reported_violations":8,"risk_level":"VERY_HIGH","population_count":15}
{"state_code":"US_DEMO","violation_type":"SUBSTANCE_ABUSE","reported_violations":1,"risk_level":"LOW","population_count":10}
{"state_code":"US_DEMO","violation_type":"SUBSTANCE_ABUSE","reported_violations":1,"risk_level":"MODERATE","population_count":15}
{"state_code":"US_DEMO","violation_type":"SUBSTANCE_ABUSE","reported_violations":1,"risk_level":"HIGH","population_count":14}
{"state_code":"US_DEMO","violation_type":"SUBSTANCE_ABUSE","reported_violations":1,"risk_level":"VERY_HIGH","population_count":9}
{"state_code":"US_DEMO","violation_type":"SUBSTANCE_ABUSE","reported_violations":2,"risk_level":"LOW","population_count":22}
{"state_code":"US_DEMO","violation_type":"SUBSTANCE_ABUSE","reported_violations":2,"risk_level":"MODERATE","population_count":19}
{"state_code":"US_DEMO","violation_type":"SUBSTANCE_ABUSE","reported_violations":2,"risk_level":"HIGH","population_count":null}
{"state_code":"US_DEMO","violation_type":"SUBSTANCE_ABUSE","reported_violations":2,"risk_level":"VERY_HIGH","population_count":11}
{"state_code":"US_DEMO","violation_type":"SUBSTANCE_ABUSE","reported_violations":3,"risk_level":"LOW","population_count":null}
{"state_code":"US_DEMO","violation_type":"SUBSTANCE_ABUSE","reported_violations":3,"risk_level":"MODERATE","population_count":23}
{"state_code":"US_DEMO","violation_type":"SUBSTANCE_ABUSE","reported_violations":3,"risk_level":"HIGH","population_count":4}
{"state_code":"US_DEMO","violation_type":"SUBSTANCE_ABUSE","reported_violations":3,"risk_level":"VERY_HIGH","population_count":5}
{"state_code":"US_DEMO","violation_type":"SUBSTANCE_ABUSE","reported_violations":4,"risk_level":"LOW","population_count":1}
{"state_code":"US_DEMO","violation_type":"SUBSTANCE_ABUSE","reported_violations":4,"risk_level":"MODERATE","population_count":null}
{"state_code":"US_DEMO","violation_type":"SUBSTANCE_ABUSE","reported_violations":4,"risk_level":"HIGH","population_count":8}
{"state_code":"US_DEMO","violation_type":"SUBSTANCE_ABUSE","reported_violations":4,"risk_level":"VERY_HIGH","population_count":15}
{"state_code":"US_DEMO","violation_type":"SUBSTANCE_ABUSE","reported_violations":5,"risk_level":"LOW","population_count":null}
{"state_code":"US_DEMO","violation_type":"SUBSTANCE_ABUSE","reported_violations":5,"risk_level":"MODERATE","population_count":null}
{"state_code":"US_DEMO","violation_type":"SUBSTANCE_ABUSE","reported_violations":5,"risk_level":"HIGH","population_count":null}
{"state_code":"US_DEMO","violation_type":"SUBSTANCE_ABUSE","reported_violations":5,"risk_level":"VERY_HIGH","population_count":19}
{"state_code":"US_DEMO","violation_type":"SUBSTANCE_ABUSE","reported_violations":6,"risk_level":"LOW","population_count":null}
{"state_code":"US_DEMO","violation_type":"SUBSTANCE_ABUSE","reported_violations":6,"risk_level":"MODERATE","population_count":15}
{"state_code":"US_DEMO","violation_type":"SUBSTANCE_ABUSE","reported_violations":6,"risk_level":"HIGH","population_count":8}
{"state_code":"US_DEMO","violation_type":"SUBSTANCE_ABUSE","reported_violations":6,"risk_level":"VERY_HIGH","population_count":2}
{"state_code":"US_DEMO","violation_type":"SUBSTANCE_ABUSE","reported_violations":7,"risk_level":"LOW","population_count":20}
{"state_code":"US_DEMO","violation_type":"SUBSTANCE_ABUSE","reported_violations":7,"risk_level":"MODERATE","population_count":7}
{"state_code":"US_DEMO","violation_type":"SUBSTANCE_ABUSE","reported_violations":7,"risk_level":"HIGH","population_count":null}
{"state_code":"US_DEMO","violation_type":"SUBSTANCE_ABUSE","reported_violations":7,"risk_level":"VERY_HIGH","population_count":17}
{"state_code":"US_DEMO","violation_type":"SUBSTANCE_ABUSE","reported_violations":8,"risk_level":"LOW","population_count":null}
{"state_code":"US_DEMO","violation_type":"SUBSTANCE_ABUSE","reported_violations":8,"risk_level":"MODERATE","population_count":20}
{"state_code":"US_DEMO","violation_type":"SUBSTANCE_ABUSE","reported_violations":8,"risk_level":"HIGH","population_count":12}
{"state_code":"US_DEMO","violation_type":"SUBSTANCE_ABUSE","reported_violations":8,"risk_level":"VERY_HIGH","population_count":14}
{"state_code":"US_DEMO","violation_type":"ABSCONSION","reported_violations":1,"risk_level":"LOW","population_count":24}
{"state_code":"US_DEMO","violation_type":"ABSCONSION","reported_violations":1,"risk_level":"MODERATE","population_count":null}
{"state_code":"US_DEMO","violation_type":"ABSCONSION","reported_violations":1,"risk_level":"HIGH","population_count":4}
{"state_code":"US_DEMO","violation_type":"ABSCONSION","reported_violations":1,"risk_level":"VERY_HIGH","population_count":23}
{"state_code":"US_DEMO","violation_type":"ABSCONSION","reported_violations":2,"risk_level":"LOW","population_count":6}
{"state_code":"US_DEMO","violation_type":"ABSCONSION","reported_violations":2,"risk_level":"MODERATE","population_count":18}
{"state_code":"US_DEMO","violation_type":"ABSCONSION","reported_violations":2,"risk_level":"HIGH","population_count":8}
{"state_code":"US_DEMO","violation_type":"ABSCONSION","reported_violations":2,"risk_level":"VERY_HIGH","population_count":25}
{"state_code":"US_DEMO","violation_type":"ABSCONSION","reported_violations":3,"risk_level":"LOW","population_count":null}
{"state_code":"US_DEMO","violation_type":"ABSCONSION","reported_violations":3,"risk_level":"MODERATE","population_count":24}
{"state_code":"US_DEMO","violation_type":"ABSCONSION","reported_violations":3,"risk_level":"HIGH","population_count":24}
{"state_code":"US_DEMO","violation_type":"ABSCONSION","reported_violations":3,"risk_level":"VERY_HIGH","population_count":7}
{"state_code":"US_DEMO","violation_type":"ABSCONSION","reported_violations":4,"risk_level":"LOW","population_count":1}
{"state_code":"US_DEMO","violation_type":"ABSCONSION","reported_violations":4,"risk_level":"MODERATE","population_count":24}
{"state_code":"US_DEMO","violation_type":"ABSCONSION","reported_violations":4,"risk_level":"HIGH","population_count":10}
{"state_code":"US_DEMO","violation_type":"ABSCONSION","reported_violations":4,"risk_level":"VERY_HIGH","population_count":23}
{"state_code":"US_DEMO","violation_type":"ABSCONSION","reported_violations":5,"risk_level":"LOW","population_count":9}
{"state_code":"US_DEMO","violation_type":"ABSCONSION","reported_violations":5,"risk_level":"MODERATE","population_count":12}
{"state_code":"US_DEMO","violation_type":"ABSCONSION","reported_violations":5,"risk_level":"HIGH","population_count":21}
{"state_code":"US_DEMO","violation_type":"ABSCONSION","reported_violations":5,"risk_level":"VERY_HIGH","population_count":1}
{"state_code":"US_DEMO","violation_type":"ABSCONSION","reported_violations":6,"risk_level":"LOW","population_count":2}
{"state_code":"US_DEMO","violation_type":"ABSCONSION","reported_violations":6,"risk_level":"MODERATE","population_count":null}
{"state_code":"US_DEMO","violation_type":"ABSCONSION","reported_violations":6,"risk_level":"HIGH","population_count":19}
{"state_code":"US_DEMO","violation_type":"ABSCONSION","reported_violations":6,"risk_level":"VERY_HIGH","population_count":14}
{"state_code":"US_DEMO","violation_type":"ABSCONSION","reported_violations":7,"risk_level":"LOW","population_count":4}
{"state_code":"US_DEMO","violation_type":"ABSCONSION","reported_violations":7,"risk_level":"MODERATE","population_count":20}
{"state_code":"US_DEMO","violation_type":"ABSCONSION","reported_violations":7,"risk_level":"HIGH","population_count":null}
{"state_code":"US_DEMO","violation_type":"ABSCONSION","reported_violations":7,"risk_level":"VERY_HIGH","population_count":15}
{"state_code":"US_DEMO","violation_type":"ABSCONSION","reported_violations":8,"risk_level":"LOW","population_count":24}
{"state_code":"US_DEMO","violation_type":"ABSCONSION","reported_violations":8,"risk_level":"MODERATE","population_count":3}
{"state_code":"US_DEMO","violation_type":"ABSCONSION","reported_violations":8,"risk_level":"HIGH","population_count":20}
{"state_code":"US_DEMO","violation_type":"ABSCONSION","reported_violations":8,"risk_level":"VERY_HIGH","population_count":4}
{"state_code":"US_DEMO","violation_type":"MISDEMEANOR","reported_violations":1,"risk_level":"LOW","population_count":6}
{"state_code":"US_DEMO","violation_type":"MISDEMEANOR","reported_violations":1,"risk_level":"MODERATE","population_count":18}
{"state_code":"US_DEMO","violation_type":"MISDEMEANOR","reported_violations":1,"risk_level":"HIGH","population_count":23}
{"state_code":"US_DEMO","violation_type":"MISDEMEANOR","reported_violations":1,"risk_level":"VERY_HIGH","population_count":3}
{"state_code":"US_DEMO","violation_type":"MISDEMEANOR","reported_violations":2,"risk_level":"LOW","population_count":14}
{"state_code":"US_DEMO","violation_type":"MISDEMEANOR","reported_violations":2,"risk_level":"MODERATE","population_count":null}
{"state_code":"US_DEMO","violation_type":"MISDEMEANOR","reported_violations":2,"risk_level":"HIGH","population_count":10}
{"state_code":"US_DEMO","violation_type":"MISDEMEANOR","reported_violations":2,"risk_level":"VERY_HIGH","population_count":null}
{"state_code":"US_DEMO","violation_type":"MISDEMEANOR","reported_violations":3,"risk_level":"LOW","population_count":15}
{"state_code":"US_DEMO","violation_type":"MISDEMEANOR","reported_violations":3,"risk_level":"MODERATE","population_count":7}
{"state_code":"US_DEMO","violation_type":"MISDEMEANOR","reported_violations":3,"risk_level":"HIGH","population_count":13}
{"state_code":"US_DEMO","violation_type":"MISDEMEANOR","reported_violations":3,"risk_level":"VERY_HIGH","population_count":22}
{"state_code":"US_DEMO","violation_type":"MISDEMEANOR","reported_violations":4,"risk_level":"LOW","population_count":10}
{"state_code":"US_DEMO","violation_type":"MISDEMEANOR","reported_violations":4,"risk_level":"MODERATE","population_count":23}
{"state_code":"US_DEMO","violation_type":"MISDEMEANOR","reported_violations":4,"risk_level":"HIGH","population_count":20}
{"state_code":"US_DEMO","violation_type":"MISDEMEANOR","reported_violations":4,"risk_level":"VERY_HIGH","population_count":16}
{"state_code":"US_DEMO","violation_type":"MISDEMEANOR","reported_violations":5,"risk_level":"LOW","population_count":null}
{"state_code":"US_DEMO","violation_type":"MISDEMEANOR","reported_violations":5,"risk_level":"MODERATE","population_count":null}
{"state_code":"US_DEMO","violation_type":"MISDEMEANOR","reported_violations":5,"risk_level":"HIGH","population_count":6}
{"state_code":"US_DEMO","violation_type":"MISDEMEANOR","reported_violations":5,"risk_level":"VERY_HIGH","population_count":10}
{"state_code":"US_DEMO","violation_type":"MISDEMEANOR","reported_violations":6,"risk_level":"LOW","population_count":25}
{"state_code":"US_DEMO","violation_type":"MISDEMEANOR","reported_violations":6,"risk_level":"MODERATE","population_count":10}
{"state_code":"US_DEMO","violation_type":"MISDEMEANOR","reported_violations":6,"risk_level":"HIGH","population_count":7}
{"state_code":"US_DEMO","violation_type":"MISDEMEANOR","reported_violations":6,"risk_level":"VERY_HIGH","population_count":5}
{"state_code":"US_DEMO","violation_type":"MISDEMEANOR","reported_violations":7,"risk_level":"LOW","population_count":12}
{"state_code":"US_DEMO","violation_type":"MISDEMEANOR","reported_violations":7,"risk_level":"MODERATE","population_count":20}
{"state_code":"US_DEMO","violation_type":"MISDEMEANOR","reported_violations":7,"risk_level":"HIGH","population_count":24}
{"state_code":"US_DEMO","violation_type":"MISDEMEANOR","reported_violations":7,"risk_level":"VERY_HIGH","population_count":13}
{"state_code":"US_DEMO","violation_type":"MISDEMEANOR","reported_violations":8,"risk_level":"LOW","population_count":null}
{"state_code":"US_DEMO","violation_type":"MISDEMEANOR","reported_violations":8,"risk_level":"MODERATE","population_count":4}
{"state_code":"US_DEMO","violation_type":"MISDEMEANOR","reported_violations":8,"risk_level":"HIGH","population_count":null}
{"state_code":"US_DEMO","violation_type":"MISDEMEANOR","reported_violations":8,"risk_level":"VERY_HIGH","population_count":2}
{"state_code":"US_DEMO","violation_type":"FELONY","reported_violations":1,"risk_level":"LOW","population_count":17}
{"state_code":"US_DEMO","violation_type":"FELONY","reported_violations":1,"risk_level":"MODERATE","population_count":24}
{"state_code":"US_DEMO","violation_type":"FELONY","reported_violations":1,"risk_level":"HIGH","population_count":null}
{"state_code":"US_DEMO","violation_type":"FELONY","reported_violations":1,"risk_level":"VERY_HIGH","population_count":null}
{"state_code":"US_DEMO","violation_type":"FELONY","reported_violations":2,"risk_level":"LOW","population_count":17}
{"state_code":"US_DEMO","violation_type":"FELONY","reported_violations":2,"risk_level":"MODERATE","population_count":2}
{"state_code":"US_DEMO","violation_type":"FELONY","reported_violations":2,"risk_level":"HIGH","population_count":23}
{"state_code":"US_DEMO","violation_type":"FELONY","reported_violations":2,"risk_level":"VERY_HIGH","population_count":21}
{"state_code":"US_DEMO","violation_type":"FELONY","reported_violations":3,"risk_level":"LOW","population_count":null}
{"state_code":"US_DEMO","violation_type":"FELONY","reported_violations":3,"risk_level":"MODERATE","population_count":null}
{"state_code":"US_DEMO","violation_type":"FELONY","reported_violations":3,"risk_level":"HIGH","population_count":null}
{"state_code":"US_DEMO","violation_type":"FELONY","reported_violations":3,"risk_level":"VERY_HIGH","population_count":null}
{"state_code":"US_DEMO","violation_type":"FELONY","reported_violations":4,"risk_level":"LOW","population_count":null}
{"state_code":"US_DEMO","violation_type":"FELONY","reported_violations":4,"risk_level":"MODERATE","population_count":12}
{"state_code":"US_DEMO","violation_type":"FELONY","reported_violations":4,"risk_level":"HIGH","population_count":12}
{"state_code":"US_DEMO","violation_type":"FELONY","reported_violations":4,"risk_level":"VERY_HIGH","population_count":11}
{"state_code":"US_DEMO","violation_type":"FELONY","reported_violations":5,"risk_level":"LOW","population_count":null}
{"state_code":"US_DEMO","violation_type":"FELONY","reported_violations":5,"risk_level":"MODERATE","population_count":null}
{"state_code":"US_DEMO","violation_type":"FELONY","reported_violations":5,"risk_level":"HIGH","population_count":null}
{"state_code":"US_DEMO","violation_type":"FELONY","reported_violations":5,"risk_level":"VERY_HIGH","population_count":20}
{"state_code":"US_DEMO","violation_type":"FELONY","reported_violations":6,"risk_level":"LOW","population_count":19}
{"state_code":"US_DEMO","violation_type":"FELONY","reported_violations":6,"risk_level":"MODERATE","population_count":null}
{"state_code":"US_DEMO","violation_type":"FELONY","reported_violations":6,"risk_level":"HIGH","population_count":12}
{"state_code":"US_DEMO","violation_type":"FELONY","reported_violations":6,"risk_level":"VERY_HIGH","population_count":16}
{"state_code":"US_DEMO","violation_type":"FELONY","reported_violations":7,"risk_level":"LOW","population_count":2}
{"state_code":"US_DEMO","violation_type":"FELONY","reported_violations":7,"risk_level":"MODERATE","population_count":null}
{"state_code":"US_DEMO","violation_type":"FELONY","reported_violations":7,"risk_level":"HIGH","population_count":null}
{"state_code":"US_DEMO","violation_type":"FELONY","reported_violations":7,"risk_level":"VERY_HIGH","population_count":8}
{"state_code":"US_DEMO","violation_type":"FELONY","reported_violations":8,"risk_level":"LOW","population_count":4}
{"state_code":"US_DEMO","violation_type":"FELONY","reported_violations":8,"risk_level":"MODERATE","population_count":3}
{"state_code":"US_DEMO","violation_type":"FELONY","reported_violations":8,"risk_level":"HIGH","population_count":6}
{"state_code":"US_DEMO","violation_type":"FELONY","reported_violations":8,"risk_level":"VERY_HIGH","population_count":14}
